odoo/addons/hr_holidays_leave_self_approve/README.rst
odoo/addons/hr_holidays_leave_self_approve/__init__.py
odoo/addons/hr_holidays_leave_self_approve/__manifest__.py
odoo/addons/hr_holidays_leave_self_approve/i18n/hr_holidays_leave_self_approve.pot
odoo/addons/hr_holidays_leave_self_approve/models/__init__.py
odoo/addons/hr_holidays_leave_self_approve/models/hr_leave.py
odoo/addons/hr_holidays_leave_self_approve/readme/CONFIGURE.rst
odoo/addons/hr_holidays_leave_self_approve/readme/CONTRIBUTORS.rst
odoo/addons/hr_holidays_leave_self_approve/readme/DESCRIPTION.rst
odoo/addons/hr_holidays_leave_self_approve/static/description/icon.png
odoo/addons/hr_holidays_leave_self_approve/static/description/index.html
odoo/addons/hr_holidays_leave_self_approve/tests/__init__.py
odoo/addons/hr_holidays_leave_self_approve/tests/test_hr_holidays_leave_self_approve.py
odoo_addon_hr_holidays_leave_self_approve-15.0.1.0.0.2.dist-info/METADATA
odoo_addon_hr_holidays_leave_self_approve-15.0.1.0.0.2.dist-info/WHEEL
odoo_addon_hr_holidays_leave_self_approve-15.0.1.0.0.2.dist-info/top_level.txt
odoo_addon_hr_holidays_leave_self_approve-15.0.1.0.0.2.dist-info/RECORD
